[
{
    "Id":"1",
    "Title":"SH1332:  12/9/2019 - 2/8/2020",
    "Data":[
        {
            "SubTitle":"Surgery: 12/11/2019 2:46:01 PM - Duration: 1 hr",
            "Data" : [
                {
                    "LotNumber":"N10190206-554",
                    "ReleaseName": "Production",
                    "UsesUsedThisProc":"1",
                    "UsesRemaining":"4",
                    "SystemName":"SH1332",
                    "ProcStart":"12/11/19 14:46:01",
                    "ProcDuration":"86.75",
                    "Name":"MONOPOLAR CURVED SCISSORS",
                    "TimeUsed":"0:42:30",
                    "PartNumber":"420179",
                    "PartVersion":"22",
                    "SerialNumber":"190206554",
                    "MaxToolUses":"10",
                    "TimeStamp":"12/11/19 16:12:43",
                    "LaserID":"61044794",
                    "FileName":"SH1332\\LogFiles\\2019\\Dec\\11\\ToolTbl.000"
                },
                {
                    "LotNumber":"N10190206-554",
                    "ReleaseName": "Production",
                    "UsesUsedThisProc":"1",
                    "UsesRemaining":"4",
                    "SystemName":"SH1332",
                    "ProcStart":"12/11/19 14:46:01",
                    "ProcDuration":"86.75",
                    "Name":"MONOPOLAR CURVED SCISSORS",
                    "TimeUsed":"0:42:30",
                    "PartNumber":"420179",
                    "PartVersion":"22",
                    "SerialNumber":"190206554",
                    "MaxToolUses":"10",
                    "TimeStamp":"12/11/19 16:12:43",
                    "LaserID":"61044794",
                    "FileName":"SH1332\\LogFiles\\2019\\Dec\\11\\ToolTbl.000"
                },
                {
                    "LotNumber":"N10190206-554",
                    "ReleaseName": "Production",
                    "UsesUsedThisProc":"1",
                    "UsesRemaining":"4",
                    "SystemName":"SH1332",
                    "ProcStart":"12/11/19 14:46:01",
                    "ProcDuration":"86.75",
                    "Name":"MONOPOLAR CURVED SCISSORS",
                    "TimeUsed":"0:42:30",
                    "PartNumber":"420179",
                    "PartVersion":"22",
                    "SerialNumber":"190206554",
                    "MaxToolUses":"10",
                    "TimeStamp":"12/11/19 16:12:43",
                    "LaserID":"61044794",
                    "FileName":"SH1332\\LogFiles\\2019\\Dec\\11\\ToolTbl.000"
                },
                {
                    "LotNumber":"N10190206-554",
                    "ReleaseName": "Production",
                    "UsesUsedThisProc":"1",
                    "UsesRemaining":"4",
                    "SystemName":"SH1332",
                    "ProcStart":"12/11/19 14:46:01",
                    "ProcDuration":"86.75",
                    "Name":"MONOPOLAR CURVED SCISSORS",
                    "TimeUsed":"0:42:30",
                    "PartNumber":"420179",
                    "PartVersion":"22",
                    "SerialNumber":"190206554",
                    "MaxToolUses":"10",
                    "TimeStamp":"12/11/19 16:12:43",
                    "LaserID":"61044794",
                    "FileName":"SH1332\\LogFiles\\2019\\Dec\\11\\ToolTbl.000"
                },
                {
                    "LotNumber":"N10190206-554",
                    "ReleaseName": "Production",
                    "UsesUsedThisProc":"1",
                    "UsesRemaining":"4",
                    "SystemName":"SH1332",
                    "ProcStart":"12/11/19 14:46:01",
                    "ProcDuration":"86.75",
                    "Name":"MONOPOLAR CURVED SCISSORS",
                    "TimeUsed":"0:42:30",
                    "PartNumber":"420179",
                    "PartVersion":"22",
                    "SerialNumber":"190206554",
                    "MaxToolUses":"10",
                    "TimeStamp":"12/11/19 16:12:43",
                    "LaserID":"61044794",
                    "FileName":"SH1332\\LogFiles\\2019\\Dec\\11\\ToolTbl.000"
                }
            ]
        },

        {
            "SubTitle":"12/11/2019 6:30:47 PM - 22008-- INF: Inserted tool was not accepted - Reason: NO_CANNULA",
            "Data" : [
                {
                    "LotNumber":"N10190206-554",
                    "ReleaseName": "Production",
                    "UsesUsedThisProc":"1",
                    "UsesRemaining":"4",
                    "SystemName":"SH1332",
                    "ProcStart":"12/11/19 14:46:01",
                    "ProcDuration":"86.75",
                    "Name":"MONOPOLAR CURVED SCISSORS",
                    "TimeUsed":"0:42:30",
                    "PartNumber":"420179",
                    "PartVersion":"22",
                    "SerialNumber":"190206554",
                    "MaxToolUses":"10",
                    "TimeStamp":"12/11/19 16:12:43",
                    "LaserID":"61044794",
                    "FileName":"SH1332\\LogFiles\\2019\\Dec\\11\\ToolTbl.000"
                },
                {
                    "LotNumber":"N10190206-554",
                    "ReleaseName": "Production",
                    "UsesUsedThisProc":"1",
                    "UsesRemaining":"4",
                    "SystemName":"SH1332",
                    "ProcStart":"12/11/19 14:46:01",
                    "ProcDuration":"86.75",
                    "Name":"MONOPOLAR CURVED SCISSORS",
                    "TimeUsed":"0:42:30",
                    "PartNumber":"420179",
                    "PartVersion":"22",
                    "SerialNumber":"190206554",
                    "MaxToolUses":"10",
                    "TimeStamp":"12/11/19 16:12:43",
                    "LaserID":"61044794",
                    "FileName":"SH1332\\LogFiles\\2019\\Dec\\11\\ToolTbl.000"
                },
                {
                    "LotNumber":"N10190206-554",
                    "ReleaseName": "Production",
                    "UsesUsedThisProc":"1",
                    "UsesRemaining":"4",
                    "SystemName":"SH1332",
                    "ProcStart":"12/11/19 14:46:01",
                    "ProcDuration":"86.75",
                    "Name":"MONOPOLAR CURVED SCISSORS",
                    "TimeUsed":"0:42:30",
                    "PartNumber":"420179",
                    "PartVersion":"22",
                    "SerialNumber":"190206554",
                    "MaxToolUses":"10",
                    "TimeStamp":"12/11/19 16:12:43",
                    "LaserID":"61044794",
                    "FileName":"SH1332\\LogFiles\\2019\\Dec\\11\\ToolTbl.000"
                },
                {
                    "LotNumber":"N10190206-554",
                    "ReleaseName": "Production",
                    "UsesUsedThisProc":"1",
                    "UsesRemaining":"4",
                    "SystemName":"SH1332",
                    "ProcStart":"12/11/19 14:46:01",
                    "ProcDuration":"86.75",
                    "Name":"MONOPOLAR CURVED SCISSORS",
                    "TimeUsed":"0:42:30",
                    "PartNumber":"420179",
                    "PartVersion":"22",
                    "SerialNumber":"190206554",
                    "MaxToolUses":"10",
                    "TimeStamp":"12/11/19 16:12:43",
                    "LaserID":"61044794",
                    "FileName":"SH1332\\LogFiles\\2019\\Dec\\11\\ToolTbl.000"
                },
                {
                    "LotNumber":"N10190206-554",
                    "ReleaseName": "Production",
                    "UsesUsedThisProc":"1",
                    "UsesRemaining":"4",
                    "SystemName":"SH1332",
                    "ProcStart":"12/11/19 14:46:01",
                    "ProcDuration":"86.75",
                    "Name":"MONOPOLAR CURVED SCISSORS",
                    "TimeUsed":"0:42:30",
                    "PartNumber":"420179",
                    "PartVersion":"22",
                    "SerialNumber":"190206554",
                    "MaxToolUses":"10",
                    "TimeStamp":"12/11/19 16:12:43",
                    "LaserID":"61044794",
                    "FileName":"SH1332\\LogFiles\\2019\\Dec\\11\\ToolTbl.000"
                }
            ]
        },
        {
            "SubTitle":"Surgery: 12/18/2019 2:49:15 PM - Duration: 1 hr",
            "Data" : [
                {
                    "LotNumber":"N10190206-554",
                    "ReleaseName": "Production",
                    "UsesUsedThisProc":"1",
                    "UsesRemaining":"4",
                    "SystemName":"SH1332",
                    "ProcStart":"12/11/19 14:46:01",
                    "ProcDuration":"86.75",
                    "Name":"MONOPOLAR CURVED SCISSORS",
                    "TimeUsed":"0:42:30",
                    "PartNumber":"420179",
                    "PartVersion":"22",
                    "SerialNumber":"190206554",
                    "MaxToolUses":"10",
                    "TimeStamp":"12/11/19 16:12:43",
                    "LaserID":"61044794",
                    "FileName":"SH1332\\LogFiles\\2019\\Dec\\11\\ToolTbl.000"
                },
                {
                    "LotNumber":"N10190206-554",
                    "ReleaseName": "Production",
                    "UsesUsedThisProc":"1",
                    "UsesRemaining":"4",
                    "SystemName":"SH1332",
                    "ProcStart":"12/11/19 14:46:01",
                    "ProcDuration":"86.75",
                    "Name":"MONOPOLAR CURVED SCISSORS",
                    "TimeUsed":"0:42:30",
                    "PartNumber":"420179",
                    "PartVersion":"22",
                    "SerialNumber":"190206554",
                    "MaxToolUses":"10",
                    "TimeStamp":"12/11/19 16:12:43",
                    "LaserID":"61044794",
                    "FileName":"SH1332\\LogFiles\\2019\\Dec\\11\\ToolTbl.000"
                },
                {
                    "LotNumber":"N10190206-554",
                    "ReleaseName": "Production",
                    "UsesUsedThisProc":"1",
                    "UsesRemaining":"4",
                    "SystemName":"SH1332",
                    "ProcStart":"12/11/19 14:46:01",
                    "ProcDuration":"86.75",
                    "Name":"MONOPOLAR CURVED SCISSORS",
                    "TimeUsed":"0:42:30",
                    "PartNumber":"420179",
                    "PartVersion":"22",
                    "SerialNumber":"190206554",
                    "MaxToolUses":"10",
                    "TimeStamp":"12/11/19 16:12:43",
                    "LaserID":"61044794",
                    "FileName":"SH1332\\LogFiles\\2019\\Dec\\11\\ToolTbl.000"
                },
                {
                    "LotNumber":"N10190206-554",
                    "ReleaseName": "Production",
                    "UsesUsedThisProc":"1",
                    "UsesRemaining":"4",
                    "SystemName":"SH1332",
                    "ProcStart":"12/11/19 14:46:01",
                    "ProcDuration":"86.75",
                    "Name":"MONOPOLAR CURVED SCISSORS",
                    "TimeUsed":"0:42:30",
                    "PartNumber":"420179",
                    "PartVersion":"22",
                    "SerialNumber":"190206554",
                    "MaxToolUses":"10",
                    "TimeStamp":"12/11/19 16:12:43",
                    "LaserID":"61044794",
                    "FileName":"SH1332\\LogFiles\\2019\\Dec\\11\\ToolTbl.000"
                },
                {
                    "LotNumber":"N10190206-554",
                    "ReleaseName": "Production",
                    "UsesUsedThisProc":"1",
                    "UsesRemaining":"4",
                    "SystemName":"SH1332",
                    "ProcStart":"12/11/19 14:46:01",
                    "ProcDuration":"86.75",
                    "Name":"MONOPOLAR CURVED SCISSORS",
                    "TimeUsed":"0:42:30",
                    "PartNumber":"420179",
                    "PartVersion":"22",
                    "SerialNumber":"190206554",
                    "MaxToolUses":"10",
                    "TimeStamp":"12/11/19 16:12:43",
                    "LaserID":"61044794",
                    "FileName":"SH1332\\LogFiles\\2019\\Dec\\11\\ToolTbl.000"
                }
            ]
        },

        {
            "SubTitle":"Surgery: 12/18/2019 6:06:15 PM - Duration: 57 min",
            "Data" : [
                {
                    "LotNumber":"N10190206-554",
                    "ReleaseName": "Production",
                    "UsesUsedThisProc":"1",
                    "UsesRemaining":"4",
                    "SystemName":"SH1332",
                    "ProcStart":"12/11/19 14:46:01",
                    "ProcDuration":"86.75",
                    "Name":"MONOPOLAR CURVED SCISSORS",
                    "TimeUsed":"0:42:30",
                    "PartNumber":"420179",
                    "PartVersion":"22",
                    "SerialNumber":"190206554",
                    "MaxToolUses":"10",
                    "TimeStamp":"12/11/19 16:12:43",
                    "LaserID":"61044794",
                    "FileName":"SH1332\\LogFiles\\2019\\Dec\\11\\ToolTbl.000"
                },
                {
                    "LotNumber":"N10190206-554",
                    "ReleaseName": "Production",
                    "UsesUsedThisProc":"1",
                    "UsesRemaining":"4",
                    "SystemName":"SH1332",
                    "ProcStart":"12/11/19 14:46:01",
                    "ProcDuration":"86.75",
                    "Name":"MONOPOLAR CURVED SCISSORS",
                    "TimeUsed":"0:42:30",
                    "PartNumber":"420179",
                    "PartVersion":"22",
                    "SerialNumber":"190206554",
                    "MaxToolUses":"10",
                    "TimeStamp":"12/11/19 16:12:43",
                    "LaserID":"61044794",
                    "FileName":"SH1332\\LogFiles\\2019\\Dec\\11\\ToolTbl.000"
                },
                {
                    "LotNumber":"N10190206-554",
                    "ReleaseName": "Production",
                    "UsesUsedThisProc":"1",
                    "UsesRemaining":"4",
                    "SystemName":"SH1332",
                    "ProcStart":"12/11/19 14:46:01",
                    "ProcDuration":"86.75",
                    "Name":"MONOPOLAR CURVED SCISSORS",
                    "TimeUsed":"0:42:30",
                    "PartNumber":"420179",
                    "PartVersion":"22",
                    "SerialNumber":"190206554",
                    "MaxToolUses":"10",
                    "TimeStamp":"12/11/19 16:12:43",
                    "LaserID":"61044794",
                    "FileName":"SH1332\\LogFiles\\2019\\Dec\\11\\ToolTbl.000"
                },
                {
                    "LotNumber":"N10190206-554",
                    "ReleaseName": "Production",
                    "UsesUsedThisProc":"1",
                    "UsesRemaining":"4",
                    "SystemName":"SH1332",
                    "ProcStart":"12/11/19 14:46:01",
                    "ProcDuration":"86.75",
                    "Name":"MONOPOLAR CURVED SCISSORS",
                    "TimeUsed":"0:42:30",
                    "PartNumber":"420179",
                    "PartVersion":"22",
                    "SerialNumber":"190206554",
                    "MaxToolUses":"10",
                    "TimeStamp":"12/11/19 16:12:43",
                    "LaserID":"61044794",
                    "FileName":"SH1332\\LogFiles\\2019\\Dec\\11\\ToolTbl.000"
                },
                {
                    "LotNumber":"N10190206-554",
                    "ReleaseName": "Production",
                    "UsesUsedThisProc":"1",
                    "UsesRemaining":"4",
                    "SystemName":"SH1332",
                    "ProcStart":"12/11/19 14:46:01",
                    "ProcDuration":"86.75",
                    "Name":"MONOPOLAR CURVED SCISSORS",
                    "TimeUsed":"0:42:30",
                    "PartNumber":"420179",
                    "PartVersion":"22",
                    "SerialNumber":"190206554",
                    "MaxToolUses":"10",
                    "TimeStamp":"12/11/19 16:12:43",
                    "LaserID":"61044794",
                    "FileName":"SH1332\\LogFiles\\2019\\Dec\\11\\ToolTbl.000"
                }
            ]
        },

        {
            "SubTitle":"CRM Case(SR: 0700521623/ FSO:0) - 12/30/2019 04:52:11 - Onsite not connecting",
            "Data" : [
                {
                    "LotNumber":"N10190206-554",
                    "ReleaseName": "Production",
                    "UsesUsedThisProc":"1",
                    "UsesRemaining":"4",
                    "SystemName":"SH1332",
                    "ProcStart":"12/11/19 14:46:01",
                    "ProcDuration":"86.75",
                    "Name":"MONOPOLAR CURVED SCISSORS",
                    "TimeUsed":"0:42:30",
                    "PartNumber":"420179",
                    "PartVersion":"22",
                    "SerialNumber":"190206554",
                    "MaxToolUses":"10",
                    "TimeStamp":"12/11/19 16:12:43",
                    "LaserID":"61044794",
                    "FileName":"SH1332\\LogFiles\\2019\\Dec\\11\\ToolTbl.000"
                },
                {
                    "LotNumber":"N10190206-554",
                    "ReleaseName": "Production",
                    "UsesUsedThisProc":"1",
                    "UsesRemaining":"4",
                    "SystemName":"SH1332",
                    "ProcStart":"12/11/19 14:46:01",
                    "ProcDuration":"86.75",
                    "Name":"MONOPOLAR CURVED SCISSORS",
                    "TimeUsed":"0:42:30",
                    "PartNumber":"420179",
                    "PartVersion":"22",
                    "SerialNumber":"190206554",
                    "MaxToolUses":"10",
                    "TimeStamp":"12/11/19 16:12:43",
                    "LaserID":"61044794",
                    "FileName":"SH1332\\LogFiles\\2019\\Dec\\11\\ToolTbl.000"
                },
                {
                    "LotNumber":"N10190206-554",
                    "ReleaseName": "Production",
                    "UsesUsedThisProc":"1",
                    "UsesRemaining":"4",
                    "SystemName":"SH1332",
                    "ProcStart":"12/11/19 14:46:01",
                    "ProcDuration":"86.75",
                    "Name":"MONOPOLAR CURVED SCISSORS",
                    "TimeUsed":"0:42:30",
                    "PartNumber":"420179",
                    "PartVersion":"22",
                    "SerialNumber":"190206554",
                    "MaxToolUses":"10",
                    "TimeStamp":"12/11/19 16:12:43",
                    "LaserID":"61044794",
                    "FileName":"SH1332\\LogFiles\\2019\\Dec\\11\\ToolTbl.000"
                },
                {
                    "LotNumber":"N10190206-554",
                    "ReleaseName": "Production",
                    "UsesUsedThisProc":"1",
                    "UsesRemaining":"4",
                    "SystemName":"SH1332",
                    "ProcStart":"12/11/19 14:46:01",
                    "ProcDuration":"86.75",
                    "Name":"MONOPOLAR CURVED SCISSORS",
                    "TimeUsed":"0:42:30",
                    "PartNumber":"420179",
                    "PartVersion":"22",
                    "SerialNumber":"190206554",
                    "MaxToolUses":"10",
                    "TimeStamp":"12/11/19 16:12:43",
                    "LaserID":"61044794",
                    "FileName":"SH1332\\LogFiles\\2019\\Dec\\11\\ToolTbl.000"
                },
                {
                    "LotNumber":"N10190206-554",
                    "ReleaseName": "Production",
                    "UsesUsedThisProc":"1",
                    "UsesRemaining":"4",
                    "SystemName":"SH1332",
                    "ProcStart":"12/11/19 14:46:01",
                    "ProcDuration":"86.75",
                    "Name":"MONOPOLAR CURVED SCISSORS",
                    "TimeUsed":"0:42:30",
                    "PartNumber":"420179",
                    "PartVersion":"22",
                    "SerialNumber":"190206554",
                    "MaxToolUses":"10",
                    "TimeStamp":"12/11/19 16:12:43",
                    "LaserID":"61044794",
                    "FileName":"SH1332\\LogFiles\\2019\\Dec\\11\\ToolTbl.000"
                }
            ]
        }

        
]
},
{
    "Id":"2",
    "Title":"SH1332:  12/9/2019 - 2/8/2020",
    "Data":[

        {
            "SubTitle":"Surgery: 12/18/2019 6:06:15 PM - Duration: 57 min",
            "Data" : [
                {
                    "LotNumber":"N10190206-554",
                    "ReleaseName": "Production",
                    "UsesUsedThisProc":"1",
                    "UsesRemaining":"4",
                    "SystemName":"SH1332",
                    "ProcStart":"12/11/19 14:46:01",
                    "ProcDuration":"86.75",
                    "Name":"MONOPOLAR CURVED SCISSORS",
                    "TimeUsed":"0:42:30",
                    "PartNumber":"420179",
                    "PartVersion":"22",
                    "SerialNumber":"190206554",
                    "MaxToolUses":"10",
                    "TimeStamp":"12/11/19 16:12:43",
                    "LaserID":"61044794",
                    "FileName":"SH1332\\LogFiles\\2019\\Dec\\11\\ToolTbl.000"
                },
                {
                    "LotNumber":"N10190206-554",
                    "ReleaseName": "Production",
                    "UsesUsedThisProc":"1",
                    "UsesRemaining":"4",
                    "SystemName":"SH1332",
                    "ProcStart":"12/11/19 14:46:01",
                    "ProcDuration":"86.75",
                    "Name":"MONOPOLAR CURVED SCISSORS",
                    "TimeUsed":"0:42:30",
                    "PartNumber":"420179",
                    "PartVersion":"22",
                    "SerialNumber":"190206554",
                    "MaxToolUses":"10",
                    "TimeStamp":"12/11/19 16:12:43",
                    "LaserID":"61044794",
                    "FileName":"SH1332\\LogFiles\\2019\\Dec\\11\\ToolTbl.000"
                },
                {
                    "LotNumber":"N10190206-554",
                    "ReleaseName": "Production",
                    "UsesUsedThisProc":"1",
                    "UsesRemaining":"4",
                    "SystemName":"SH1332",
                    "ProcStart":"12/11/19 14:46:01",
                    "ProcDuration":"86.75",
                    "Name":"MONOPOLAR CURVED SCISSORS",
                    "TimeUsed":"0:42:30",
                    "PartNumber":"420179",
                    "PartVersion":"22",
                    "SerialNumber":"190206554",
                    "MaxToolUses":"10",
                    "TimeStamp":"12/11/19 16:12:43",
                    "LaserID":"61044794",
                    "FileName":"SH1332\\LogFiles\\2019\\Dec\\11\\ToolTbl.000"
                },
                {
                    "LotNumber":"N10190206-554",
                    "ReleaseName": "Production",
                    "UsesUsedThisProc":"1",
                    "UsesRemaining":"4",
                    "SystemName":"SH1332",
                    "ProcStart":"12/11/19 14:46:01",
                    "ProcDuration":"86.75",
                    "Name":"MONOPOLAR CURVED SCISSORS",
                    "TimeUsed":"0:42:30",
                    "PartNumber":"420179",
                    "PartVersion":"22",
                    "SerialNumber":"190206554",
                    "MaxToolUses":"10",
                    "TimeStamp":"12/11/19 16:12:43",
                    "LaserID":"61044794",
                    "FileName":"SH1332\\LogFiles\\2019\\Dec\\11\\ToolTbl.000"
                },
                {
                    "LotNumber":"N10190206-554",
                    "ReleaseName": "Production",
                    "UsesUsedThisProc":"1",
                    "UsesRemaining":"4",
                    "SystemName":"SH1332",
                    "ProcStart":"12/11/19 14:46:01",
                    "ProcDuration":"86.75",
                    "Name":"MONOPOLAR CURVED SCISSORS",
                    "TimeUsed":"0:42:30",
                    "PartNumber":"420179",
                    "PartVersion":"22",
                    "SerialNumber":"190206554",
                    "MaxToolUses":"10",
                    "TimeStamp":"12/11/19 16:12:43",
                    "LaserID":"61044794",
                    "FileName":"SH1332\\LogFiles\\2019\\Dec\\11\\ToolTbl.000"
                }
            ]
        },

        {
            "SubTitle":"CRM Case(SR: 0700521623/ FSO:0) - 12/30/2019 04:52:11 - Onsite not connecting",
            "Data" : [
                {
                    "LotNumber":"N10190206-554",
                    "ReleaseName": "Production",
                    "UsesUsedThisProc":"1",
                    "UsesRemaining":"4",
                    "SystemName":"SH1332",
                    "ProcStart":"12/11/19 14:46:01",
                    "ProcDuration":"86.75",
                    "Name":"MONOPOLAR CURVED SCISSORS",
                    "TimeUsed":"0:42:30",
                    "PartNumber":"420179",
                    "PartVersion":"22",
                    "SerialNumber":"190206554",
                    "MaxToolUses":"10",
                    "TimeStamp":"12/11/19 16:12:43",
                    "LaserID":"61044794",
                    "FileName":"SH1332\\LogFiles\\2019\\Dec\\11\\ToolTbl.000"
                },
                {
                    "LotNumber":"N10190206-554",
                    "ReleaseName": "Production",
                    "UsesUsedThisProc":"1",
                    "UsesRemaining":"4",
                    "SystemName":"SH1332",
                    "ProcStart":"12/11/19 14:46:01",
                    "ProcDuration":"86.75",
                    "Name":"MONOPOLAR CURVED SCISSORS",
                    "TimeUsed":"0:42:30",
                    "PartNumber":"420179",
                    "PartVersion":"22",
                    "SerialNumber":"190206554",
                    "MaxToolUses":"10",
                    "TimeStamp":"12/11/19 16:12:43",
                    "LaserID":"61044794",
                    "FileName":"SH1332\\LogFiles\\2019\\Dec\\11\\ToolTbl.000"
                },
                {
                    "LotNumber":"N10190206-554",
                    "ReleaseName": "Production",
                    "UsesUsedThisProc":"1",
                    "UsesRemaining":"4",
                    "SystemName":"SH1332",
                    "ProcStart":"12/11/19 14:46:01",
                    "ProcDuration":"86.75",
                    "Name":"MONOPOLAR CURVED SCISSORS",
                    "TimeUsed":"0:42:30",
                    "PartNumber":"420179",
                    "PartVersion":"22",
                    "SerialNumber":"190206554",
                    "MaxToolUses":"10",
                    "TimeStamp":"12/11/19 16:12:43",
                    "LaserID":"61044794",
                    "FileName":"SH1332\\LogFiles\\2019\\Dec\\11\\ToolTbl.000"
                },
                {
                    "LotNumber":"N10190206-554",
                    "ReleaseName": "Production",
                    "UsesUsedThisProc":"1",
                    "UsesRemaining":"4",
                    "SystemName":"SH1332",
                    "ProcStart":"12/11/19 14:46:01",
                    "ProcDuration":"86.75",
                    "Name":"MONOPOLAR CURVED SCISSORS",
                    "TimeUsed":"0:42:30",
                    "PartNumber":"420179",
                    "PartVersion":"22",
                    "SerialNumber":"190206554",
                    "MaxToolUses":"10",
                    "TimeStamp":"12/11/19 16:12:43",
                    "LaserID":"61044794",
                    "FileName":"SH1332\\LogFiles\\2019\\Dec\\11\\ToolTbl.000"
                },
                {
                    "LotNumber":"N10190206-554",
                    "ReleaseName": "Production",
                    "UsesUsedThisProc":"1",
                    "UsesRemaining":"4",
                    "SystemName":"SH1332",
                    "ProcStart":"12/11/19 14:46:01",
                    "ProcDuration":"86.75",
                    "Name":"MONOPOLAR CURVED SCISSORS",
                    "TimeUsed":"0:42:30",
                    "PartNumber":"420179",
                    "PartVersion":"22",
                    "SerialNumber":"190206554",
                    "MaxToolUses":"10",
                    "TimeStamp":"12/11/19 16:12:43",
                    "LaserID":"61044794",
                    "FileName":"SH1332\\LogFiles\\2019\\Dec\\11\\ToolTbl.000"
                }
            ]
        }

        
]
},
{
    "Id":"3",
    "Title":"SH1332:  12/9/2019 - 2/8/2020",
    "Data":[
        {
            "SubTitle":"Surgery: 12/11/2019 2:46:01 PM - Duration: 1 hr",
            "Data" : [
                {
                    "LotNumber":"N10190206-554",
                    "ReleaseName": "Production",
                    "UsesUsedThisProc":"1",
                    "UsesRemaining":"4",
                    "SystemName":"SH1332",
                    "ProcStart":"12/11/19 14:46:01",
                    "ProcDuration":"86.75",
                    "Name":"MONOPOLAR CURVED SCISSORS",
                    "TimeUsed":"0:42:30",
                    "PartNumber":"420179",
                    "PartVersion":"22",
                    "SerialNumber":"190206554",
                    "MaxToolUses":"10",
                    "TimeStamp":"12/11/19 16:12:43",
                    "LaserID":"61044794",
                    "FileName":"SH1332\\LogFiles\\2019\\Dec\\11\\ToolTbl.000"
                },
                {
                    "LotNumber":"N10190206-554",
                    "ReleaseName": "Production",
                    "UsesUsedThisProc":"1",
                    "UsesRemaining":"4",
                    "SystemName":"SH1332",
                    "ProcStart":"12/11/19 14:46:01",
                    "ProcDuration":"86.75",
                    "Name":"MONOPOLAR CURVED SCISSORS",
                    "TimeUsed":"0:42:30",
                    "PartNumber":"420179",
                    "PartVersion":"22",
                    "SerialNumber":"190206554",
                    "MaxToolUses":"10",
                    "TimeStamp":"12/11/19 16:12:43",
                    "LaserID":"61044794",
                    "FileName":"SH1332\\LogFiles\\2019\\Dec\\11\\ToolTbl.000"
                },
                {
                    "LotNumber":"N10190206-554",
                    "ReleaseName": "Production",
                    "UsesUsedThisProc":"1",
                    "UsesRemaining":"4",
                    "SystemName":"SH1332",
                    "ProcStart":"12/11/19 14:46:01",
                    "ProcDuration":"86.75",
                    "Name":"MONOPOLAR CURVED SCISSORS",
                    "TimeUsed":"0:42:30",
                    "PartNumber":"420179",
                    "PartVersion":"22",
                    "SerialNumber":"190206554",
                    "MaxToolUses":"10",
                    "TimeStamp":"12/11/19 16:12:43",
                    "LaserID":"61044794",
                    "FileName":"SH1332\\LogFiles\\2019\\Dec\\11\\ToolTbl.000"
                },
                {
                    "LotNumber":"N10190206-554",
                    "ReleaseName": "Production",
                    "UsesUsedThisProc":"1",
                    "UsesRemaining":"4",
                    "SystemName":"SH1332",
                    "ProcStart":"12/11/19 14:46:01",
                    "ProcDuration":"86.75",
                    "Name":"MONOPOLAR CURVED SCISSORS",
                    "TimeUsed":"0:42:30",
                    "PartNumber":"420179",
                    "PartVersion":"22",
                    "SerialNumber":"190206554",
                    "MaxToolUses":"10",
                    "TimeStamp":"12/11/19 16:12:43",
                    "LaserID":"61044794",
                    "FileName":"SH1332\\LogFiles\\2019\\Dec\\11\\ToolTbl.000"
                },
                {
                    "LotNumber":"N10190206-554",
                    "ReleaseName": "Production",
                    "UsesUsedThisProc":"1",
                    "UsesRemaining":"4",
                    "SystemName":"SH1332",
                    "ProcStart":"12/11/19 14:46:01",
                    "ProcDuration":"86.75",
                    "Name":"MONOPOLAR CURVED SCISSORS",
                    "TimeUsed":"0:42:30",
                    "PartNumber":"420179",
                    "PartVersion":"22",
                    "SerialNumber":"190206554",
                    "MaxToolUses":"10",
                    "TimeStamp":"12/11/19 16:12:43",
                    "LaserID":"61044794",
                    "FileName":"SH1332\\LogFiles\\2019\\Dec\\11\\ToolTbl.000"
                }
            ]
        },

        {
            "SubTitle":"Surgery: 12/18/2019 6:06:15 PM - Duration: 57 min",
            "Data" : [
                {
                    "LotNumber":"N10190206-554",
                    "ReleaseName": "Production",
                    "UsesUsedThisProc":"1",
                    "UsesRemaining":"4",
                    "SystemName":"SH1332",
                    "ProcStart":"12/11/19 14:46:01",
                    "ProcDuration":"86.75",
                    "Name":"MONOPOLAR CURVED SCISSORS",
                    "TimeUsed":"0:42:30",
                    "PartNumber":"420179",
                    "PartVersion":"22",
                    "SerialNumber":"190206554",
                    "MaxToolUses":"10",
                    "TimeStamp":"12/11/19 16:12:43",
                    "LaserID":"61044794",
                    "FileName":"SH1332\\LogFiles\\2019\\Dec\\11\\ToolTbl.000"
                },
                {
                    "LotNumber":"N10190206-554",
                    "ReleaseName": "Production",
                    "UsesUsedThisProc":"1",
                    "UsesRemaining":"4",
                    "SystemName":"SH1332",
                    "ProcStart":"12/11/19 14:46:01",
                    "ProcDuration":"86.75",
                    "Name":"MONOPOLAR CURVED SCISSORS",
                    "TimeUsed":"0:42:30",
                    "PartNumber":"420179",
                    "PartVersion":"22",
                    "SerialNumber":"190206554",
                    "MaxToolUses":"10",
                    "TimeStamp":"12/11/19 16:12:43",
                    "LaserID":"61044794",
                    "FileName":"SH1332\\LogFiles\\2019\\Dec\\11\\ToolTbl.000"
                },
                {
                    "LotNumber":"N10190206-554",
                    "ReleaseName": "Production",
                    "UsesUsedThisProc":"1",
                    "UsesRemaining":"4",
                    "SystemName":"SH1332",
                    "ProcStart":"12/11/19 14:46:01",
                    "ProcDuration":"86.75",
                    "Name":"MONOPOLAR CURVED SCISSORS",
                    "TimeUsed":"0:42:30",
                    "PartNumber":"420179",
                    "PartVersion":"22",
                    "SerialNumber":"190206554",
                    "MaxToolUses":"10",
                    "TimeStamp":"12/11/19 16:12:43",
                    "LaserID":"61044794",
                    "FileName":"SH1332\\LogFiles\\2019\\Dec\\11\\ToolTbl.000"
                },
                {
                    "LotNumber":"N10190206-554",
                    "ReleaseName": "Production",
                    "UsesUsedThisProc":"1",
                    "UsesRemaining":"4",
                    "SystemName":"SH1332",
                    "ProcStart":"12/11/19 14:46:01",
                    "ProcDuration":"86.75",
                    "Name":"MONOPOLAR CURVED SCISSORS",
                    "TimeUsed":"0:42:30",
                    "PartNumber":"420179",
                    "PartVersion":"22",
                    "SerialNumber":"190206554",
                    "MaxToolUses":"10",
                    "TimeStamp":"12/11/19 16:12:43",
                    "LaserID":"61044794",
                    "FileName":"SH1332\\LogFiles\\2019\\Dec\\11\\ToolTbl.000"
                },
                {
                    "LotNumber":"N10190206-554",
                    "ReleaseName": "Production",
                    "UsesUsedThisProc":"1",
                    "UsesRemaining":"4",
                    "SystemName":"SH1332",
                    "ProcStart":"12/11/19 14:46:01",
                    "ProcDuration":"86.75",
                    "Name":"MONOPOLAR CURVED SCISSORS",
                    "TimeUsed":"0:42:30",
                    "PartNumber":"420179",
                    "PartVersion":"22",
                    "SerialNumber":"190206554",
                    "MaxToolUses":"10",
                    "TimeStamp":"12/11/19 16:12:43",
                    "LaserID":"61044794",
                    "FileName":"SH1332\\LogFiles\\2019\\Dec\\11\\ToolTbl.000"
                }
            ]
        },

        {
            "SubTitle":"CRM Case(SR: 0700521623/ FSO:0) - 12/30/2019 04:52:11 - Onsite not connecting",
            "Data" : [
                {
                    "LotNumber":"N10190206-554",
                    "ReleaseName": "Production",
                    "UsesUsedThisProc":"1",
                    "UsesRemaining":"4",
                    "SystemName":"SH1332",
                    "ProcStart":"12/11/19 14:46:01",
                    "ProcDuration":"86.75",
                    "Name":"MONOPOLAR CURVED SCISSORS",
                    "TimeUsed":"0:42:30",
                    "PartNumber":"420179",
                    "PartVersion":"22",
                    "SerialNumber":"190206554",
                    "MaxToolUses":"10",
                    "TimeStamp":"12/11/19 16:12:43",
                    "LaserID":"61044794",
                    "FileName":"SH1332\\LogFiles\\2019\\Dec\\11\\ToolTbl.000"
                },
                {
                    "LotNumber":"N10190206-554",
                    "ReleaseName": "Production",
                    "UsesUsedThisProc":"1",
                    "UsesRemaining":"4",
                    "SystemName":"SH1332",
                    "ProcStart":"12/11/19 14:46:01",
                    "ProcDuration":"86.75",
                    "Name":"MONOPOLAR CURVED SCISSORS",
                    "TimeUsed":"0:42:30",
                    "PartNumber":"420179",
                    "PartVersion":"22",
                    "SerialNumber":"190206554",
                    "MaxToolUses":"10",
                    "TimeStamp":"12/11/19 16:12:43",
                    "LaserID":"61044794",
                    "FileName":"SH1332\\LogFiles\\2019\\Dec\\11\\ToolTbl.000"
                },
                {
                    "LotNumber":"N10190206-554",
                    "ReleaseName": "Production",
                    "UsesUsedThisProc":"1",
                    "UsesRemaining":"4",
                    "SystemName":"SH1332",
                    "ProcStart":"12/11/19 14:46:01",
                    "ProcDuration":"86.75",
                    "Name":"MONOPOLAR CURVED SCISSORS",
                    "TimeUsed":"0:42:30",
                    "PartNumber":"420179",
                    "PartVersion":"22",
                    "SerialNumber":"190206554",
                    "MaxToolUses":"10",
                    "TimeStamp":"12/11/19 16:12:43",
                    "LaserID":"61044794",
                    "FileName":"SH1332\\LogFiles\\2019\\Dec\\11\\ToolTbl.000"
                },
                {
                    "LotNumber":"N10190206-554",
                    "ReleaseName": "Production",
                    "UsesUsedThisProc":"1",
                    "UsesRemaining":"4",
                    "SystemName":"SH1332",
                    "ProcStart":"12/11/19 14:46:01",
                    "ProcDuration":"86.75",
                    "Name":"MONOPOLAR CURVED SCISSORS",
                    "TimeUsed":"0:42:30",
                    "PartNumber":"420179",
                    "PartVersion":"22",
                    "SerialNumber":"190206554",
                    "MaxToolUses":"10",
                    "TimeStamp":"12/11/19 16:12:43",
                    "LaserID":"61044794",
                    "FileName":"SH1332\\LogFiles\\2019\\Dec\\11\\ToolTbl.000"
                },
                {
                    "LotNumber":"N10190206-554",
                    "ReleaseName": "Production",
                    "UsesUsedThisProc":"1",
                    "UsesRemaining":"4",
                    "SystemName":"SH1332",
                    "ProcStart":"12/11/19 14:46:01",
                    "ProcDuration":"86.75",
                    "Name":"MONOPOLAR CURVED SCISSORS",
                    "TimeUsed":"0:42:30",
                    "PartNumber":"420179",
                    "PartVersion":"22",
                    "SerialNumber":"190206554",
                    "MaxToolUses":"10",
                    "TimeStamp":"12/11/19 16:12:43",
                    "LaserID":"61044794",
                    "FileName":"SH1332\\LogFiles\\2019\\Dec\\11\\ToolTbl.000"
                }
            ]
        }

        
]
}
    
]
